scrapy_webarchive/__init__.py
scrapy_webarchive/constants.py
scrapy_webarchive/downloadermiddlewares.py
scrapy_webarchive/exceptions.py
scrapy_webarchive/extensions.py
scrapy_webarchive/models.py
scrapy_webarchive/resolvers.py
scrapy_webarchive/spidermiddlewares.py
scrapy_webarchive/strategies.py
scrapy_webarchive/utils.py
scrapy_webarchive/cdxj/__init__.py
scrapy_webarchive/cdxj/indexers.py
scrapy_webarchive/cdxj/models.py
scrapy_webarchive/wacz/__init__.py
scrapy_webarchive/wacz/constants.py
scrapy_webarchive/wacz/creator.py
scrapy_webarchive/wacz/storages.py
scrapy_webarchive/wacz/wacz_file.py
scrapy_webarchive/wacz/zip_utils.py
scrapy_webarchive/warc/__init__.py
scrapy_webarchive/warc/readers.py
scrapy_webarchive/warc/transformers.py
scrapy_webarchive/warc/utils.py
scrapy_webarchive/warc/warc.py
scrapy_webarchive/warc/writers.py
scrapy_webarchive-0.4.1.dist-info/METADATA
scrapy_webarchive-0.4.1.dist-info/WHEEL
scrapy_webarchive-0.4.1.dist-info/top_level.txt
scrapy_webarchive-0.4.1.dist-info/RECORD
