Metadata-Version: 2.1
Name: scrapy-webarchive
Version: 0.4.1
Summary: A webarchive extension for Scrapy
Project-URL: Documentation, https://developers.thequestionmark.org/scrapy-webarchive/
Project-URL: Repository, https://github.com/q-m/scrapy-webarchive
Keywords: Scrapy,Webarchive,WARC,WACZ
Classifier: Development Status :: 4 - Beta
Classifier: Programming Language :: Python :: 3
Classifier: Programming Language :: Python
Requires-Python: <3.13,>=3.7
Requires-Dist: Scrapy <2.12,>=2.9
Requires-Dist: warcio ==1.7.4
Requires-Dist: warc-knot ==0.2.5
Requires-Dist: wacz ==0.5.0
Requires-Dist: cdxj-indexer ==1.4.5
Provides-Extra: all
Requires-Dist: boto3 ; extra == 'all'
Requires-Dist: google-cloud-storage ; extra == 'all'
Provides-Extra: aws
Requires-Dist: boto3 ; extra == 'aws'
Provides-Extra: gcs
Requires-Dist: google-cloud-storage ; extra == 'gcs'
